llama_index/readers/weather/__init__.py
llama_index/readers/weather/base.py
llama_index_readers_weather-0.4.1.dist-info/METADATA
llama_index_readers_weather-0.4.1.dist-info/WHEEL
llama_index_readers_weather-0.4.1.dist-info/licenses/LICENSE
llama_index_readers_weather-0.4.1.dist-info/RECORD
