Metadata-Version: 2.4
Name: llama-index-readers-weather
Version: 0.4.1
Summary: llama-index readers weather integration
Author-email: Your Name <you@example.com>
Maintainer: iamadhee
License-Expression: MIT
License-File: LICENSE
Keywords: openweather,weather
Requires-Python: <4.0,>=3.9
Requires-Dist: llama-index-core<0.15,>=0.13.0
Requires-Dist: pyowm<4,>=3.3.0
